babbot.py
babbot-1.0.0.dist-info/DESCRIPTION.rst
babbot-1.0.0.dist-info/METADATA
babbot-1.0.0.dist-info/RECORD
babbot-1.0.0.dist-info/WHEEL
babbot-1.0.0.dist-info/metadata.json
babbot-1.0.0.dist-info/top_level.txt
