Metadata-Version: 2.0
Name: babbot
Version: 1.0.0
Summary: A package for make kakao-talk school meal bot easily
Home-page: https://github.com/RISMME/bob-bot
Author: RISM
Author-email: python@istruly.sexy
License: MIT
Keywords: School Meal Kakaotalk Chatbot
Platform: UNKNOWN
Classifier: Development Status :: 3 - Alpha
Classifier: Framework :: Flask
Classifier: Intended Audience :: Education
Classifier: Topic :: Education
Classifier: License :: OSI Approved :: MIT License
Classifier: Programming Language :: Python :: 3
Classifier: Programming Language :: Python :: 3.4
Classifier: Programming Language :: Python :: 3.5
Classifier: Programming Language :: Python :: 3.6
Classifier: Programming Language :: Python :: 3.7
Requires-Dist: flask
Requires-Dist: schapi
